lazyrepr.py
lazyrepr-0.0.4.dist-info/METADATA
lazyrepr-0.0.4.dist-info/WHEEL
lazyrepr-0.0.4.dist-info/licenses/LICENSE.txt
lazyrepr-0.0.4.dist-info/RECORD
