Metadata-Version: 2.4
Name: lazyrepr
Version: 0.0.4
Summary: Mixin class for concise object representation
Project-URL: homepage, https://github.com/furechan/lazyrepr
Author-email: furechan <furechan@xsmail.com>
License-File: LICENSE.txt
Keywords: mixin,repr
Classifier: License :: OSI Approved :: MIT License
Classifier: Operating System :: OS Independent
Classifier: Programming Language :: Python :: 3
Requires-Python: >=3.9
